jaygoga_orchestra/__init__.py
jaygoga_orchestra/test_script.py
jaygoga_orchestra/test_script1.py
jaygoga_orchestra/legacy/aiflow/__init__.py
jaygoga_orchestra/legacy/aiflow/agent.py
jaygoga_orchestra/legacy/aiflow/crew.py
jaygoga_orchestra/legacy/aiflow/task.py
jaygoga_orchestra/legacy/aiflow/cli/__init__.py
jaygoga_orchestra/legacy/aiflow/cli/base.py
jaygoga_orchestra/legacy/aiflow/cli/beautiful_cli.py
jaygoga_orchestra/legacy/aiflow/cli/conversation_agent.py
jaygoga_orchestra/legacy/aiflow/cli/create.py
jaygoga_orchestra/legacy/aiflow/cli/deploy.py
jaygoga_orchestra/legacy/aiflow/cli/evaluate.py
jaygoga_orchestra/legacy/aiflow/cli/main.py
jaygoga_orchestra/legacy/aiflow/cli/manage.py
jaygoga_orchestra/legacy/aiflow/cli/train.py
jaygoga_orchestra/legacy/aiflow/core/__init__.py
jaygoga_orchestra/legacy/aiflow/core/agent.py
jaygoga_orchestra/legacy/aiflow/core/performance_monitor.py
jaygoga_orchestra/legacy/aiflow/core/result_validator.py
jaygoga_orchestra/legacy/aiflow/core/task.py
jaygoga_orchestra/legacy/aiflow/core/team.py
jaygoga_orchestra/legacy/aiflow/interfaces/__init__.py
jaygoga_orchestra/legacy/aiflow/interfaces/intervention.py
jaygoga_orchestra/legacy/aiflow/interfaces/terminal_interface.py
jaygoga_orchestra/legacy/aiflow/knowledge/__init__.py
jaygoga_orchestra/legacy/aiflow/knowledge/base.py
jaygoga_orchestra/legacy/aiflow/knowledge/rag_tool.py
jaygoga_orchestra/legacy/aiflow/knowledge/readers.py
jaygoga_orchestra/legacy/aiflow/knowledge/sources.py
jaygoga_orchestra/legacy/aiflow/llm/anthropic_client.py
jaygoga_orchestra/legacy/aiflow/llm/base_client.py
jaygoga_orchestra/legacy/aiflow/llm/factory.py
jaygoga_orchestra/legacy/aiflow/llm/gemini_client.py
jaygoga_orchestra/legacy/aiflow/llm/groq_client.py
jaygoga_orchestra/legacy/aiflow/llm/openai_client.py
jaygoga_orchestra/legacy/aiflow/memory/__init__.py
jaygoga_orchestra/legacy/aiflow/memory/base.py
jaygoga_orchestra/legacy/aiflow/memory/manager.py
jaygoga_orchestra/legacy/aiflow/memory/storage.py
jaygoga_orchestra-1.0.2.dist-info/licenses/LICENSE
jaygoga_orchestra-1.0.2.dist-info/METADATA
jaygoga_orchestra-1.0.2.dist-info/WHEEL
jaygoga_orchestra-1.0.2.dist-info/entry_points.txt
jaygoga_orchestra-1.0.2.dist-info/top_level.txt
jaygoga_orchestra-1.0.2.dist-info/RECORD
