Metadata-Version: 2.4
Name: jaygoga-orchestra
Version: 1.0.2
Summary: JayGoga-Orchestra - Advanced AI Agent Orchestration Framework
Home-page: https://github.com/AIMLDev726/jaygoga_orchestra
Author: AIMLDev726
Author-email: AIMLDev726 <aistudentlearn4@gmail.com>
License: MIT
Project-URL: Homepage, https://github.com/AIMLDev726/jaygoga_orchestra
Project-URL: Documentation, https://docs.jaygoga.ai
Project-URL: Repository, https://github.com/AIMLDev726/jaygoga_orchestra
Project-URL: Issues, https://github.com/AIMLDev726/jaygoga_orchestra/issues
Keywords: ai,agents,workflow,automation,llm,orchestration,jaygoga
Classifier: Development Status :: 4 - Beta
Classifier: Intended Audience :: Developers
Classifier: License :: OSI Approved :: MIT License
Classifier: Operating System :: OS Independent
Classifier: Programming Language :: Python :: 3
Classifier: Programming Language :: Python :: 3.8
Classifier: Programming Language :: Python :: 3.9
Classifier: Programming Language :: Python :: 3.10
Classifier: Programming Language :: Python :: 3.11
Classifier: Programming Language :: Python :: 3.12
Classifier: Topic :: Software Development :: Libraries :: Python Modules
Classifier: Topic :: Scientific/Engineering :: Artificial Intelligence
Requires-Python: >=3.8
License-File: LICENSE
Requires-Dist: pydantic>=2.4.2
Requires-Dist: openai>=1.13.3
Requires-Dist: litellm>=1.74.9
Requires-Dist: instructor>=1.3.3
Requires-Dist: pdfplumber>=0.11.4
Requires-Dist: regex>=2024.9.11
Requires-Dist: opentelemetry-api>=1.30.0
Requires-Dist: opentelemetry-sdk>=1.30.0
Requires-Dist: opentelemetry-exporter-otlp-proto-http>=1.30.0
Requires-Dist: chromadb>=0.5.23
Requires-Dist: tokenizers>=0.20.3
Requires-Dist: onnxruntime>=1.22.0
Requires-Dist: openpyxl>=3.1.5
Requires-Dist: pyvis>=0.3.2
Requires-Dist: python-dotenv>=1.0.0
Requires-Dist: pyjwt>=2.9.0
Requires-Dist: click>=8.1.7
Requires-Dist: appdirs>=1.4.4
Requires-Dist: jsonref>=1.1.0
Requires-Dist: json-repair>=0.25.2
Requires-Dist: tomli-w>=1.1.0
Requires-Dist: tomli>=2.0.2
Requires-Dist: blinker>=1.9.0
Requires-Dist: json5>=0.10.0
Requires-Dist: portalocker>=2.7.0
Requires-Dist: rich>=13.0.0
Requires-Dist: typing-extensions>=4.0.0
Requires-Dist: requests>=2.25.0
Requires-Dist: anthropic>=0.3.0
Requires-Dist: langchain>=0.1.0
Requires-Dist: langchain-community>=0.0.1
Requires-Dist: langchain-openai>=0.0.1
Requires-Dist: tiktoken>=0.5.0
Requires-Dist: tenacity>=8.0.0
Requires-Dist: PyYAML>=6.0.0
Requires-Dist: jsonschema>=4.0.0
Requires-Dist: sqlalchemy>=2.0.0
Requires-Dist: aiofiles>=23.0.0
Requires-Dist: httpx>=0.24.0
Requires-Dist: aiohttp>=3.8.0
Requires-Dist: pandas>=2.2.3
Requires-Dist: numpy>=1.24.0
Provides-Extra: dev
Requires-Dist: pytest>=7.0.0; extra == "dev"
Requires-Dist: pytest-asyncio>=0.21.0; extra == "dev"
Requires-Dist: black>=23.0.0; extra == "dev"
Requires-Dist: isort>=5.12.0; extra == "dev"
Requires-Dist: flake8>=6.0.0; extra == "dev"
Requires-Dist: mypy>=1.0.0; extra == "dev"
Requires-Dist: build>=0.10.0; extra == "dev"
Requires-Dist: twine>=4.0.0; extra == "dev"
Provides-Extra: vectordbs
Requires-Dist: faiss-cpu>=1.7.0; extra == "vectordbs"
Requires-Dist: pinecone-client>=2.2.0; extra == "vectordbs"
Requires-Dist: weaviate-client>=3.15.0; extra == "vectordbs"
Requires-Dist: qdrant-client>=1.6.0; extra == "vectordbs"
Requires-Dist: pgvector>=0.2.0; extra == "vectordbs"
Requires-Dist: lancedb>=0.20.0; extra == "vectordbs"
Requires-Dist: milvus>=2.5.10; extra == "vectordbs"
Provides-Extra: tools
Requires-Dist: arxiv>=1.4.0; extra == "tools"
Requires-Dist: newspaper4k>=0.9.0; extra == "tools"
Requires-Dist: youtube-transcript-api>=0.6.0; extra == "tools"
Requires-Dist: googlemaps>=4.10.0; extra == "tools"
Requires-Dist: matplotlib>=3.7.0; extra == "tools"
Requires-Dist: opencv-python>=4.8.0; extra == "tools"
Requires-Dist: selenium>=4.15.0; extra == "tools"
Requires-Dist: beautifulsoup4>=4.12.0; extra == "tools"
Provides-Extra: files
Requires-Dist: pypdf>=3.0.0; extra == "files"
Requires-Dist: python-docx>=0.8.11; extra == "files"
Requires-Dist: markdown>=3.4.0; extra == "files"
Requires-Dist: unstructured>=0.10.0; extra == "files"
Requires-Dist: docling>=2.12.0; extra == "files"
Provides-Extra: memory
Requires-Dist: mem0ai>=0.1.94; extra == "memory"
Requires-Dist: redis>=4.5.0; extra == "memory"
Requires-Dist: postgresql>=0.8.0; extra == "memory"
Requires-Dist: sqlite3>=3.40.0; extra == "memory"
Provides-Extra: all
Requires-Dist: jaygoga-orchestra[vectordbs]; extra == "all"
Requires-Dist: jaygoga-orchestra[tools]; extra == "all"
Requires-Dist: jaygoga-orchestra[files]; extra == "all"
Requires-Dist: jaygoga-orchestra[memory]; extra == "all"
Dynamic: author
Dynamic: home-page
Dynamic: license-file
Dynamic: requires-python
